<?xml version="1.0" encoding="utf-8" ?>
<Defs>
	<!-- 폰 헤드 애니메이션 -->
	<!-- 유란 -->
	<YR_Hentai_Prime_AnimationBed.BedAnimationDef>
		<defName>YR_Milking_Face_Yuran</defName>
		<autoDurationTicksSetting>true</autoDurationTicksSetting>
		<isPawnTextureReplace>true</isPawnTextureReplace>
		<setPawnColor>false</setPawnColor>
		<!-- <logCurrentOffset>true</logCurrentOffset> -->
		<pawnRenderNodeTagDef>Head</pawnRenderNodeTagDef>
		<animationSynchro>true</animationSynchro>
		<bedAnimationSettings>
			<li>
				<tick>0</tick>
				<offset>(0.0,0.06,0.26)</offset>
				<graphicData>
					<texPath>Yuran/Yuranlike/Addon/MilkingMachine/Face/1_south</texPath>
					<graphicClass>Graphic_Single</graphicClass>
					<drawSize>(1.25, 1.25)</drawSize>
				</graphicData>
			</li>
			<li>
				<tick>4</tick>
				<offset>(0.0,0.06,0.26)</offset>
				<graphicData>
					<texPath>Yuran/Yuranlike/Addon/MilkingMachine/Face/2_south</texPath>
					<graphicClass>Graphic_Single</graphicClass>
					<drawSize>(1.25, 1.25)</drawSize>
				</graphicData>
			</li>
			<li>
				<tick>8</tick>
				<offset>(0.0,0.06,0.26)</offset>
				<graphicData>
					<texPath>Yuran/Yuranlike/Addon/MilkingMachine/Face/3_south</texPath>
					<graphicClass>Graphic_Single</graphicClass>
					<drawSize>(1.25, 1.25)</drawSize>
				</graphicData>
			</li>
			<li>
				<tick>12</tick>
				<offset>(0.0,0.06,0.26)</offset>
				<graphicData>
					<texPath>Yuran/Yuranlike/Addon/MilkingMachine/Face/4_south</texPath>
					<graphicClass>Graphic_Single</graphicClass>
					<drawSize>(1.25, 1.25)</drawSize>
				</graphicData>
			</li>
			<li>
				<tick>24</tick>
				<offset>(0.0,0.06,0.26)</offset>
				<graphicData>
					<texPath>Yuran/Yuranlike/Addon/MilkingMachine/Face/5_south</texPath>
					<graphicClass>Graphic_Single</graphicClass>
					<drawSize>(1.25, 1.25)</drawSize>
				</graphicData>
			</li>
			<li>
				<tick>35</tick>
				<offset>(0.0,0.06,0.26)</offset>
				<graphicData>
					<texPath>Yuran/Yuranlike/Addon/MilkingMachine/Face/6_south</texPath>
					<graphicClass>Graphic_Single</graphicClass>
					<drawSize>(1.25, 1.25)</drawSize>
				</graphicData>
			</li>
			<li>
				<tick>55</tick>
				<offset>(0.0,0.06,0.26)</offset>
				<graphicData>
					<texPath>Yuran/Yuranlike/Addon/MilkingMachine/Face/7_south</texPath>
					<graphicClass>Graphic_Single</graphicClass>
					<drawSize>(1.25, 1.25)</drawSize>
				</graphicData>
			</li>
		</bedAnimationSettings>
	</YR_Hentai_Prime_AnimationBed.BedAnimationDef>
	<YR_Hentai_Prime_AnimationBed.BedAnimationDef>
		<defName>YR_Milking_Face_Yuran_Miko</defName>
		<autoDurationTicksSetting>true</autoDurationTicksSetting>
		<isPawnTextureReplace>true</isPawnTextureReplace>
		<setPawnColor>false</setPawnColor>
		<!-- <logCurrentOffset>true</logCurrentOffset> -->
		<pawnRenderNodeTagDef>Head</pawnRenderNodeTagDef>
		<animationSynchro>true</animationSynchro>
		<bedAnimationSettings>
			<li>
				<tick>0</tick>
				<offset>(0.0,0.06,0.26)</offset>
				<graphicData>
					<texPath>Yuran/Yuranlike/Addon/MilkingMachine/Face/1_south</texPath>
					<graphicClass>Graphic_Single</graphicClass>
					<drawSize>(1.25, 1.25)</drawSize>
				</graphicData>
			</li>
			<li>
				<tick>4</tick>
				<offset>(0.0,0.06,0.26)</offset>
				<graphicData>
					<texPath>Yuran/Yuranlike/Addon/MilkingMachine/Face/2_south</texPath>
					<graphicClass>Graphic_Single</graphicClass>
					<drawSize>(1.25, 1.25)</drawSize>
				</graphicData>
			</li>
			<li>
				<tick>8</tick>
				<offset>(0.0,0.06,0.26)</offset>
				<graphicData>
					<texPath>Yuran/Yuranlike/Addon/MilkingMachine/Face/3_south</texPath>
					<graphicClass>Graphic_Single</graphicClass>
					<drawSize>(1.25, 1.25)</drawSize>
				</graphicData>
			</li>
			<li>
				<tick>12</tick>
				<offset>(0.0,0.06,0.26)</offset>
				<graphicData>
					<texPath>Yuran/Yuranlike/Addon/MilkingMachine/Face/4_south</texPath>
					<graphicClass>Graphic_Single</graphicClass>
					<drawSize>(1.25, 1.25)</drawSize>
				</graphicData>
			</li>
			<li>
				<tick>24</tick>
				<offset>(0.0,0.06,0.26)</offset>
				<graphicData>
					<texPath>Yuran/Yuranlike/Addon/MilkingMachine/Face/5_south</texPath>
					<graphicClass>Graphic_Single</graphicClass>
					<drawSize>(1.25, 1.25)</drawSize>
				</graphicData>
			</li>
			<li>
				<tick>35</tick>
				<offset>(0.0,0.06,0.26)</offset>
				<graphicData>
					<texPath>Yuran/Yuranlike/Addon/MilkingMachine/Face/6_south</texPath>
					<graphicClass>Graphic_Single</graphicClass>
					<drawSize>(1.25, 1.25)</drawSize>
				</graphicData>
			</li>
			<li>
				<tick>55</tick>
				<offset>(0.0,0.06,0.26)</offset>
				<graphicData>
					<texPath>Yuran/Yuranlike/Addon/MilkingMachine/Face/7_south</texPath>
					<graphicClass>Graphic_Single</graphicClass>
					<drawSize>(1.25, 1.25)</drawSize>
				</graphicData>
			</li>
		</bedAnimationSettings>
	</YR_Hentai_Prime_AnimationBed.BedAnimationDef>
	<!-- 유란 -->
	<YR_Hentai_Prime_AnimationBed.BedAnimationDef>
		<defName>YR_Milking_Body_Yuran</defName>
		<!-- 이거의 durationTicks은 comp에서 자동으로 조정 -->
		<autoDurationTicksSetting>true</autoDurationTicksSetting>
		<!--폰 애니메이션과 침대 애니메이션의 총 틱의 강제 매치 -->
		<isPawnTextureReplace>true</isPawnTextureReplace>
		<!-- 텍스처 판정을 폰 바디 랜더로 바꿈 -->
		<setPawnColor>false</setPawnColor>
		<!-- 이걸 해줘야 색상이 스킨 컬러, 셰이더 적용 됨. 다만 유란 같은 경우 적용이 되면 안되니깐 꺼둠 -->
		<pawnRenderNodeTagDef>Body</pawnRenderNodeTagDef>
		<!-- 이 텍스처는 어느 랜더 노드 태그 쓰는지 -->
		<animationSynchro>false</animationSynchro>
		<!--동일한 pawnRenderNodeTagDef를 가진 애니메이션과 움직임을 싱크로 -->
		<!-- <logCurrentOffset>true</logCurrentOffset> -->
		<bedAnimationSettings>
			<li>
				<tick>0</tick>
				<offset>(0.0, 0.01,0.25)</offset>
				<graphicData>
					<texPath>Yuran/Things/Building/Furniture/MilkingMachine/Body/Race/Yuran/Thin/1_south</texPath>
					<graphicClass>Graphic_Single</graphicClass>
					<drawSize>(1.25, 1.25)</drawSize>
				</graphicData>
			</li>
			<li>
				<tick>4</tick>
				<offset>(0.0, 0.01,0.25)</offset>
				<graphicData>
					<texPath>Yuran/Things/Building/Furniture/MilkingMachine/Body/Race/Yuran/Thin/2_south</texPath>
					<graphicClass>Graphic_Single</graphicClass>
					<drawSize>(1.25, 1.25)</drawSize>
				</graphicData>
			</li>
			<li>
				<tick>8</tick>
				<offset>(0.0,0.01,0.25)</offset>
				<graphicData>
					<texPath>Yuran/Things/Building/Furniture/MilkingMachine/Body/Race/Yuran/Thin/3_south</texPath>
					<graphicClass>Graphic_Single</graphicClass>
					<drawSize>(1.25, 1.25)</drawSize>
				</graphicData>
			</li>
			<li>
				<tick>12</tick>
				<offset>(0.0,0.01,0.25)</offset>
				<graphicData>
					<texPath>Yuran/Things/Building/Furniture/MilkingMachine/Body/Race/Yuran/Thin/4_south</texPath>
					<graphicClass>Graphic_Single</graphicClass>
					<drawSize>(1.25, 1.25)</drawSize>
				</graphicData>
			</li>
			<li>
				<tick>40</tick>
				<offset>(0.0,0.01,0.25)</offset>
				<graphicData>
					<texPath>Yuran/Things/Building/Furniture/MilkingMachine/Body/Race/Yuran/Thin/5_south</texPath>
					<graphicClass>Graphic_Single</graphicClass>
					<drawSize>(1.25, 1.25)</drawSize>
				</graphicData>
			</li>
			<li>
				<tick>55</tick>
				<offset>(0.0,0.01,0.25)</offset>
				<graphicData>
					<texPath>Yuran/Things/Building/Furniture/MilkingMachine/Body/Race/Yuran/Thin/6_south</texPath>
					<graphicClass>Graphic_Single</graphicClass>
					<drawSize>(1.25, 1.25)</drawSize>
				</graphicData>
			</li>
		</bedAnimationSettings>
	</YR_Hentai_Prime_AnimationBed.BedAnimationDef>
	<!-- 유란자궁 -->
	<YR_Hentai_Prime_AnimationBed.BedAnimationDef>
		<defName>YR_Milking_Uterus_Yuran</defName>
		<autoDurationTicksSetting>true</autoDurationTicksSetting>
		<bedAnimationSettings>
			<li>
				<tick>0</tick>
				<offset>(0.0,1,0)</offset>
				<graphicData>
					<texPath>Yuran/Things/Building/Furniture/MilkingMachine/Body/Uterus/Yuran/1</texPath>
					<graphicClass>Graphic_Single</graphicClass>
					<drawSize>(2.25, 2.25)</drawSize>
					<shaderType>Transparent</shaderType>
				</graphicData>
			</li>
			<li>
				<tick>4</tick>
				<offset>(0.0,1,0)</offset>
				<graphicData>
					<texPath>Yuran/Things/Building/Furniture/MilkingMachine/Body/Uterus/Yuran/2</texPath>
					<graphicClass>Graphic_Single</graphicClass>
					<drawSize>(2.25, 2.25)</drawSize>
					<shaderType>Transparent</shaderType>
				</graphicData>
			</li>
			<li>
				<tick>8</tick>
				<offset>(0.0,1,0)</offset>
				<graphicData>
					<texPath>Yuran/Things/Building/Furniture/MilkingMachine/Body/Uterus/Yuran/3</texPath>
					<graphicClass>Graphic_Single</graphicClass>
					<drawSize>(2.25, 2.25)</drawSize>
					<shaderType>Transparent</shaderType>
				</graphicData>
			</li>
			<li>
				<tick>12</tick>
				<offset>(0.0,1,0)</offset>
				<graphicData>
					<texPath>Yuran/Things/Building/Furniture/MilkingMachine/Body/Uterus/Yuran/4</texPath>
					<graphicClass>Graphic_Single</graphicClass>
					<drawSize>(2.25, 2.25)</drawSize>
					<shaderType>Transparent</shaderType>
				</graphicData>
			</li>
			<li>
				<tick>45</tick>
				<offset>(0.0,1,0)</offset>
				<graphicData>
					<texPath>Yuran/Things/Building/Furniture/MilkingMachine/Body/Uterus/Yuran/5</texPath>
					<graphicClass>Graphic_Single</graphicClass>
					<drawSize>(2.25, 2.25)</drawSize>
					<shaderType>Transparent</shaderType>
				</graphicData>
			</li>
			<li>
				<tick>55</tick>
				<offset>(0.0,1,0)</offset>
				<graphicData>
					<texPath>Yuran/Things/Building/Furniture/MilkingMachine/Body/Uterus/Yuran/6</texPath>
					<graphicClass>Graphic_Single</graphicClass>
					<drawSize>(2.25, 2.25)</drawSize>
					<shaderType>Transparent</shaderType>
				</graphicData>
			</li>
		</bedAnimationSettings>
	</YR_Hentai_Prime_AnimationBed.BedAnimationDef>
	<!-- 유란 파워모드1 -->
	<!-- 유란 -->
	<YR_Hentai_Prime_AnimationBed.BedAnimationDef>
		<defName>YR_Milking_Body_Yuran_PowerA</defName>
		<!-- 이거의 durationTicks은 comp에서 자동으로 조정 -->
		<autoDurationTicksSetting>true</autoDurationTicksSetting>
		<!--폰 애니메이션과 침대 애니메이션의 총 틱의 강제 매치 -->
		<isPawnTextureReplace>true</isPawnTextureReplace>
		<!-- 텍스처 판정을 폰 바디 랜더로 바꿈 -->
		<setPawnColor>false</setPawnColor>
		<!-- 이걸 해줘야 색상이 스킨 컬러, 셰이더 적용 됨. 다만 유란 같은 경우 적용이 되면 안되니깐 꺼둠 -->
		<pawnRenderNodeTagDef>Body</pawnRenderNodeTagDef>
		<!-- 이 텍스처는 어느 랜더 노드 태그 쓰는지 -->
		<animationSynchro>false</animationSynchro>
		<!--동일한 pawnRenderNodeTagDef를 가진 애니메이션과 움직임을 싱크로 -->
		<bedAnimationSettings>
			<li>
				<tick>0</tick>
				<offset>(0.0, 0.01,0.25)</offset>
				<graphicData>
					<texPath>Yuran/Things/Building/Furniture/MilkingMachine/Body/Race/Yuran/Thin/1_south</texPath>
					<graphicClass>Graphic_Single</graphicClass>
					<drawSize>(1.25, 1.25)</drawSize>
				</graphicData>
			</li>
			<li>
				<tick>10</tick>
				<offset>(0.0, 0.01,0.25)</offset>
				<graphicData>
					<texPath>Yuran/Things/Building/Furniture/MilkingMachine/Body/Race/Yuran/Thin/L1_south</texPath>
					<graphicClass>Graphic_Single</graphicClass>
					<drawSize>(1.25, 1.25)</drawSize>
				</graphicData>
			</li>
			<li>
				<tick>20</tick>
				<offset>(0.0, 0.01,0.25)</offset>
				<graphicData>
					<texPath>Yuran/Things/Building/Furniture/MilkingMachine/Body/Race/Yuran/Thin/L2_south</texPath>
					<graphicClass>Graphic_Single</graphicClass>
					<drawSize>(1.25, 1.25)</drawSize>
				</graphicData>
			</li>
			<li>
				<tick>30</tick>
				<offset>(0.0, 0.01,0.25)</offset>
				<graphicData>
					<texPath>Yuran/Things/Building/Furniture/MilkingMachine/Body/Race/Yuran/Thin/4_south</texPath>
					<graphicClass>Graphic_Single</graphicClass>
					<drawSize>(1.25, 1.25)</drawSize>
				</graphicData>
			</li>
			<li>
				<tick>40</tick>
				<offset>(0.0, 0.01,0.25)</offset>
				<graphicData>
					<texPath>Yuran/Things/Building/Furniture/MilkingMachine/Body/Race/Yuran/Thin/R3_south</texPath>
					<graphicClass>Graphic_Single</graphicClass>
					<drawSize>(1.25, 1.25)</drawSize>
				</graphicData>
			</li>
			<li>
				<tick>50</tick>
				<offset>(0.0, 0.01,0.25)</offset>
				<graphicData>
					<texPath>Yuran/Things/Building/Furniture/MilkingMachine/Body/Race/Yuran/Thin/R4_south</texPath>
					<graphicClass>Graphic_Single</graphicClass>
					<drawSize>(1.25, 1.25)</drawSize>
				</graphicData>
			</li>
		</bedAnimationSettings>
	</YR_Hentai_Prime_AnimationBed.BedAnimationDef>
	<!-- 유란자궁 -->
	<YR_Hentai_Prime_AnimationBed.BedAnimationDef>
		<defName>YR_Milking_Uterus_Yuran_PowerA</defName>
		<autoDurationTicksSetting>true</autoDurationTicksSetting>
		<bedAnimationSettings>
			<li>
				<tick>0</tick>
				<offset>(0.0,1,0)</offset>
				<graphicData>
					<texPath>Yuran/Things/Building/Furniture/MilkingMachine/Body/Uterus/Yuran/1</texPath>
					<graphicClass>Graphic_Single</graphicClass>
					<drawSize>(2.25, 2.25)</drawSize>
					<shaderType>Transparent</shaderType>
				</graphicData>
			</li>
			<li>
				<tick>10</tick>
				<offset>(0.0,1,0)</offset>
				<graphicData>
					<texPath>Yuran/Things/Building/Furniture/MilkingMachine/Body/Uterus/Yuran/3</texPath>
					<graphicClass>Graphic_Single</graphicClass>
					<drawSize>(2.25, 2.25)</drawSize>
					<shaderType>Transparent</shaderType>
				</graphicData>
			</li>
			<li>
				<tick>20</tick>
				<offset>(0.0,1,0)</offset>
				<graphicData>
					<texPath>Yuran/Things/Building/Furniture/MilkingMachine/Body/Uterus/Yuran/L1</texPath>
					<graphicClass>Graphic_Single</graphicClass>
					<drawSize>(2.25, 2.25)</drawSize>
					<shaderType>Transparent</shaderType>
				</graphicData>
			</li>
			<li>
				<tick>30</tick>
				<offset>(0.0,1,0)</offset>
				<graphicData>
					<texPath>Yuran/Things/Building/Furniture/MilkingMachine/Body/Uterus/Yuran/4</texPath>
					<graphicClass>Graphic_Single</graphicClass>
					<drawSize>(2.25, 2.25)</drawSize>
					<shaderType>Transparent</shaderType>
				</graphicData>
			</li>
			<li>
				<tick>40</tick>
				<offset>(0.0,1,0)</offset>
				<graphicData>
					<texPath>Yuran/Things/Building/Furniture/MilkingMachine/Body/Uterus/Yuran/R2</texPath>
					<graphicClass>Graphic_Single</graphicClass>
					<drawSize>(2.25, 2.25)</drawSize>
					<shaderType>Transparent</shaderType>
				</graphicData>
			</li>
			<li>
				<tick>50</tick>
				<offset>(0.0,1,0)</offset>
				<graphicData>
					<texPath>Yuran/Things/Building/Furniture/MilkingMachine/Body/Uterus/Yuran/3</texPath>
					<graphicClass>Graphic_Single</graphicClass>
					<drawSize>(2.25, 2.25)</drawSize>
					<shaderType>Transparent</shaderType>
				</graphicData>
			</li>
		</bedAnimationSettings>
	</YR_Hentai_Prime_AnimationBed.BedAnimationDef>
	<!-- 딜도 -->
	<YR_Hentai_Prime_AnimationBed.BedAnimationDef>
		<defName>YR_Milking_Dildo_Yuran_PowerA</defName>
		<!-- 이거의 durationTicks은 comp에서 자동으로 조정 -->
		<autoDurationTicksSetting>true</autoDurationTicksSetting>
		<bedAnimationSettings>
			<li>
				<tick>0</tick>
				<offset>(0,1,-0.025)</offset>
				<graphicData>
					<texPath>Yuran/Things/Building/Furniture/MilkingMachine/Body/Dildo/1</texPath>
					<graphicClass>Graphic_Single</graphicClass>
					<drawSize>(2.25, 2.25)</drawSize>
					<shaderType>Transparent</shaderType>
				</graphicData>
			</li>
			<li>
				<tick>10</tick>
				<offset>(0,1,-0.025)</offset>
				<graphicData>
					<texPath>Yuran/Things/Building/Furniture/MilkingMachine/Body/Dildo/L1</texPath>
					<graphicClass>Graphic_Single</graphicClass>
					<drawSize>(2.25, 2.25)</drawSize>
					<shaderType>Transparent</shaderType>
				</graphicData>
			</li>
			<li>
				<tick>20</tick>
				<offset>(0,1,-0.025)</offset>
				<graphicData>
					<texPath>Yuran/Things/Building/Furniture/MilkingMachine/Body/Dildo/L2</texPath>
					<graphicClass>Graphic_Single</graphicClass>
					<drawSize>(2.25, 2.25)</drawSize>
					<shaderType>Transparent</shaderType>
				</graphicData>
			</li>
			<li>
				<tick>30</tick>
				<offset>(0,1,-0.025)</offset>
				<graphicData>
					<texPath>Yuran/Things/Building/Furniture/MilkingMachine/Body/Dildo/4</texPath>
					<graphicClass>Graphic_Single</graphicClass>
					<drawSize>(2.25, 2.25)</drawSize>
					<shaderType>Transparent</shaderType>
				</graphicData>
			</li>
			<li>
				<tick>40</tick>
				<offset>(0,1,-0.025)</offset>
				<graphicData>
					<texPath>Yuran/Things/Building/Furniture/MilkingMachine/Body/Dildo/R3</texPath>
					<graphicClass>Graphic_Single</graphicClass>
					<drawSize>(2.25, 2.25)</drawSize>
					<shaderType>Transparent</shaderType>
				</graphicData>
			</li>
			<li>
				<tick>50</tick>
				<offset>(0,1,-0.025)</offset>
				<graphicData>
					<texPath>Yuran/Things/Building/Furniture/MilkingMachine/Body/Dildo/R4</texPath>
					<graphicClass>Graphic_Single</graphicClass>
					<drawSize>(2.25, 2.25)</drawSize>
					<shaderType>Transparent</shaderType>
				</graphicData>
			</li>
		</bedAnimationSettings>
	</YR_Hentai_Prime_AnimationBed.BedAnimationDef>
	<!-- 유란 파워모드2 -->
	<!-- 유란 -->
	<YR_Hentai_Prime_AnimationBed.BedAnimationDef>
		<defName>YR_Milking_Body_Yuran_PowerB</defName>
		<!-- 이거의 durationTicks은 comp에서 자동으로 조정 -->
		<autoDurationTicksSetting>true</autoDurationTicksSetting>
		<!--폰 애니메이션과 침대 애니메이션의 총 틱의 강제 매치 -->
		<isPawnTextureReplace>true</isPawnTextureReplace>
		<!-- 텍스처 판정을 폰 바디 랜더로 바꿈 -->
		<setPawnColor>false</setPawnColor>
		<!-- 이걸 해줘야 색상이 스킨 컬러, 셰이더 적용 됨. 다만 유란 같은 경우 적용이 되면 안되니깐 꺼둠 -->
		<pawnRenderNodeTagDef>Body</pawnRenderNodeTagDef>
		<!-- 이 텍스처는 어느 랜더 노드 태그 쓰는지 -->
		<animationSynchro>false</animationSynchro>
		<!--동일한 pawnRenderNodeTagDef를 가진 애니메이션과 움직임을 싱크로 -->
		<bedAnimationSettings>
			<li>
				<tick>0</tick>
				<offset>(0.0, 0.01,0.25)</offset>
				<graphicData>
					<texPath>Yuran/Things/Building/Furniture/MilkingMachine/Body/Race/Yuran/Thin/1_south</texPath>
					<graphicClass>Graphic_Single</graphicClass>
					<drawSize>(1.25, 1.25)</drawSize>
				</graphicData>
			</li>
			<li>
				<tick>4</tick>
				<offset>(0.0, 0.01,0.25)</offset>
				<graphicData>
					<texPath>Yuran/Things/Building/Furniture/MilkingMachine/Body/Race/Yuran/Thin/2_south</texPath>
					<graphicClass>Graphic_Single</graphicClass>
					<drawSize>(1.25, 1.25)</drawSize>
				</graphicData>
			</li>
			<li>
				<tick>8</tick>
				<offset>(0.0, 0.01,0.25)</offset>
				<graphicData>
					<texPath>Yuran/Things/Building/Furniture/MilkingMachine/Body/Race/Yuran/Thin/3_south</texPath>
					<graphicClass>Graphic_Single</graphicClass>
					<drawSize>(1.25, 1.25)</drawSize>
				</graphicData>
			</li>
			<li>
				<tick>12</tick>
				<offset>(0.0, 0.01,0.25)</offset>
				<graphicData>
					<texPath>Yuran/Things/Building/Furniture/MilkingMachine/Body/Race/Yuran/Thin/4_south</texPath>
					<graphicClass>Graphic_Single</graphicClass>
					<drawSize>(1.25, 1.25)</drawSize>
				</graphicData>
			</li>
			<li>
				<tick>16</tick>
				<offset>(0.0, 0.01,0.25)</offset>
				<graphicData>
					<texPath>Yuran/Things/Building/Furniture/MilkingMachine/Body/Race/Yuran/Thin/L2_south</texPath>
					<graphicClass>Graphic_Single</graphicClass>
					<drawSize>(1.25, 1.25)</drawSize>
				</graphicData>
			</li>
			<li>
				<tick>20</tick>
				<offset>(0.0, 0.01,0.25)</offset>
				<graphicData>
					<texPath>Yuran/Things/Building/Furniture/MilkingMachine/Body/Race/Yuran/Thin/4_south</texPath>
					<graphicClass>Graphic_Single</graphicClass>
					<drawSize>(1.25, 1.25)</drawSize>
				</graphicData>
			</li>
			<li>
				<tick>24</tick>
				<offset>(0.0, 0.01,0.25)</offset>
				<graphicData>
					<texPath>Yuran/Things/Building/Furniture/MilkingMachine/Body/Race/Yuran/Thin/R3_south</texPath>
					<graphicClass>Graphic_Single</graphicClass>
					<drawSize>(1.25, 1.25)</drawSize>
				</graphicData>
			</li>
			<li>
				<tick>28</tick>
				<offset>(0.0, 0.01,0.25)</offset>
				<graphicData>
					<texPath>Yuran/Things/Building/Furniture/MilkingMachine/Body/Race/Yuran/Thin/4_south</texPath>
					<graphicClass>Graphic_Single</graphicClass>
					<drawSize>(1.25, 1.25)</drawSize>
				</graphicData>
			</li>
			<li>
				<tick>32</tick>
				<offset>(0.0, 0.01,0.25)</offset>
				<graphicData>
					<texPath>Yuran/Things/Building/Furniture/MilkingMachine/Body/Race/Yuran/Thin/L2_south</texPath>
					<graphicClass>Graphic_Single</graphicClass>
					<drawSize>(1.25, 1.25)</drawSize>
				</graphicData>
			</li>
			<li>
				<tick>36</tick>
				<offset>(0.0, 0.01,0.25)</offset>
				<graphicData>
					<texPath>Yuran/Things/Building/Furniture/MilkingMachine/Body/Race/Yuran/Thin/4_south</texPath>
					<graphicClass>Graphic_Single</graphicClass>
					<drawSize>(1.25, 1.25)</drawSize>
				</graphicData>
			</li>
			<li>
				<tick>40</tick>
				<offset>(0.0, 0.01,0.25)</offset>
				<graphicData>
					<texPath>Yuran/Things/Building/Furniture/MilkingMachine/Body/Race/Yuran/Thin/R3_south</texPath>
					<graphicClass>Graphic_Single</graphicClass>
					<drawSize>(1.25, 1.25)</drawSize>
				</graphicData>
			</li>
			<li>
				<tick>44</tick>
				<offset>(0.0, 0.01,0.25)</offset>
				<graphicData>
					<texPath>Yuran/Things/Building/Furniture/MilkingMachine/Body/Race/Yuran/Thin/4_south</texPath>
					<graphicClass>Graphic_Single</graphicClass>
					<drawSize>(1.25, 1.25)</drawSize>
				</graphicData>
			</li>
			<li>
				<tick>55</tick>
				<offset>(0.0, 0.01,0.25)</offset>
				<graphicData>
					<texPath>Yuran/Things/Building/Furniture/MilkingMachine/Body/Race/Yuran/Thin/5_south</texPath>
					<graphicClass>Graphic_Single</graphicClass>
					<drawSize>(1.25, 1.25)</drawSize>
				</graphicData>
			</li>
		</bedAnimationSettings>
	</YR_Hentai_Prime_AnimationBed.BedAnimationDef>
	<!-- 유란자궁 -->
	<YR_Hentai_Prime_AnimationBed.BedAnimationDef>
		<defName>YR_Milking_Uterus_Yuran_PowerB</defName>
		<autoDurationTicksSetting>true</autoDurationTicksSetting>
		<bedAnimationSettings>
			<li>
				<tick>0</tick>
				<offset>(0.0,1,0)</offset>
				<graphicData>
					<texPath>Yuran/Things/Building/Furniture/MilkingMachine/Body/Uterus/Yuran/1</texPath>
					<graphicClass>Graphic_Single</graphicClass>
					<drawSize>(2.25, 2.25)</drawSize>
					<shaderType>Transparent</shaderType>
				</graphicData>
			</li>
			<li>
				<tick>4</tick>
				<offset>(0.0,1,0)</offset>
				<graphicData>
					<texPath>Yuran/Things/Building/Furniture/MilkingMachine/Body/Uterus/Yuran/2</texPath>
					<graphicClass>Graphic_Single</graphicClass>
					<drawSize>(2.25, 2.25)</drawSize>
					<shaderType>Transparent</shaderType>
				</graphicData>
			</li>
			<li>
				<tick>8</tick>
				<offset>(0.0,1,0)</offset>
				<graphicData>
					<texPath>Yuran/Things/Building/Furniture/MilkingMachine/Body/Uterus/Yuran/3</texPath>
					<graphicClass>Graphic_Single</graphicClass>
					<drawSize>(2.25, 2.25)</drawSize>
					<shaderType>Transparent</shaderType>
				</graphicData>
			</li>
			<li>
				<tick>12</tick>
				<offset>(0.0,1,0)</offset>
				<graphicData>
					<texPath>Yuran/Things/Building/Furniture/MilkingMachine/Body/Uterus/Yuran/4</texPath>
					<graphicClass>Graphic_Single</graphicClass>
					<drawSize>(2.25, 2.25)</drawSize>
					<shaderType>Transparent</shaderType>
				</graphicData>
			</li>
			<li>
				<tick>16</tick>
				<offset>(0.0,1,0)</offset>
				<graphicData>
					<texPath>Yuran/Things/Building/Furniture/MilkingMachine/Body/Uterus/Yuran/L1</texPath>
					<graphicClass>Graphic_Single</graphicClass>
					<drawSize>(2.25, 2.25)</drawSize>
					<shaderType>Transparent</shaderType>
				</graphicData>
			</li>
			<li>
				<tick>20</tick>
				<offset>(0.0,1,0)</offset>
				<graphicData>
					<texPath>Yuran/Things/Building/Furniture/MilkingMachine/Body/Uterus/Yuran/4</texPath>
					<graphicClass>Graphic_Single</graphicClass>
					<drawSize>(2.25, 2.25)</drawSize>
					<shaderType>Transparent</shaderType>
				</graphicData>
			</li>
			<li>
				<tick>24</tick>
				<offset>(0.0,1,0)</offset>
				<graphicData>
					<texPath>Yuran/Things/Building/Furniture/MilkingMachine/Body/Uterus/Yuran/R2</texPath>
					<graphicClass>Graphic_Single</graphicClass>
					<drawSize>(2.25, 2.25)</drawSize>
					<shaderType>Transparent</shaderType>
				</graphicData>
			</li>
			<li>
				<tick>28</tick>
				<offset>(0.0,1,0)</offset>
				<graphicData>
					<texPath>Yuran/Things/Building/Furniture/MilkingMachine/Body/Uterus/Yuran/4</texPath>
					<graphicClass>Graphic_Single</graphicClass>
					<drawSize>(2.25, 2.25)</drawSize>
					<shaderType>Transparent</shaderType>
				</graphicData>
			</li>
			<li>
				<tick>32</tick>
				<offset>(0.0,1,0)</offset>
				<graphicData>
					<texPath>Yuran/Things/Building/Furniture/MilkingMachine/Body/Uterus/Yuran/L1</texPath>
					<graphicClass>Graphic_Single</graphicClass>
					<drawSize>(2.25, 2.25)</drawSize>
					<shaderType>Transparent</shaderType>
				</graphicData>
			</li>
			<li>
				<tick>36</tick>
				<offset>(0.0,1,0)</offset>
				<graphicData>
					<texPath>Yuran/Things/Building/Furniture/MilkingMachine/Body/Uterus/Yuran/4</texPath>
					<graphicClass>Graphic_Single</graphicClass>
					<drawSize>(2.25, 2.25)</drawSize>
					<shaderType>Transparent</shaderType>
				</graphicData>
			</li>
			<li>
				<tick>40</tick>
				<offset>(0.0,1,0)</offset>
				<graphicData>
					<texPath>Yuran/Things/Building/Furniture/MilkingMachine/Body/Uterus/Yuran/R2</texPath>
					<graphicClass>Graphic_Single</graphicClass>
					<drawSize>(2.25, 2.25)</drawSize>
					<shaderType>Transparent</shaderType>
				</graphicData>
			</li>
			<li>
				<tick>44</tick>
				<offset>(0.0,1,0)</offset>
				<graphicData>
					<texPath>Yuran/Things/Building/Furniture/MilkingMachine/Body/Uterus/Yuran/4</texPath>
					<graphicClass>Graphic_Single</graphicClass>
					<drawSize>(2.25, 2.25)</drawSize>
					<shaderType>Transparent</shaderType>
				</graphicData>
			</li>
			<li>
				<tick>55</tick>
				<offset>(0.0,1,0)</offset>
				<graphicData>
					<texPath>Yuran/Things/Building/Furniture/MilkingMachine/Body/Uterus/Yuran/5</texPath>
					<graphicClass>Graphic_Single</graphicClass>
					<drawSize>(2.25, 2.25)</drawSize>
					<shaderType>Transparent</shaderType>
				</graphicData>
			</li>
		</bedAnimationSettings>
	</YR_Hentai_Prime_AnimationBed.BedAnimationDef>
	<!-- 딜도 -->
	<YR_Hentai_Prime_AnimationBed.BedAnimationDef>
		<defName>YR_Milking_Dildo_Yuran_PowerB</defName>
		<!-- 이거의 durationTicks은 comp에서 자동으로 조정 -->
		<autoDurationTicksSetting>true</autoDurationTicksSetting>
		<bedAnimationSettings>
			<li>
				<tick>0</tick>
				<offset>(0,1,-0.025)</offset>
				<graphicData>
					<texPath>Yuran/Things/Building/Furniture/MilkingMachine/Body/Dildo/1</texPath>
					<graphicClass>Graphic_Single</graphicClass>
					<drawSize>(2.25, 2.25)</drawSize>
					<shaderType>Transparent</shaderType>
				</graphicData>
			</li>
			<li>
				<tick>4</tick>
				<offset>(0,1,-0.025)</offset>
				<graphicData>
					<texPath>Yuran/Things/Building/Furniture/MilkingMachine/Body/Dildo/2</texPath>
					<graphicClass>Graphic_Single</graphicClass>
					<drawSize>(2.25, 2.25)</drawSize>
					<shaderType>Transparent</shaderType>
				</graphicData>
			</li>
			<li>
				<tick>8</tick>
				<offset>(0,1,-0.025)</offset>
				<graphicData>
					<texPath>Yuran/Things/Building/Furniture/MilkingMachine/Body/Dildo/3</texPath>
					<graphicClass>Graphic_Single</graphicClass>
					<drawSize>(2.25, 2.25)</drawSize>
					<shaderType>Transparent</shaderType>
				</graphicData>
			</li>
			<li>
				<tick>12</tick>
				<offset>(0,1,-0.025)</offset>
				<graphicData>
					<texPath>Yuran/Things/Building/Furniture/MilkingMachine/Body/Dildo/4</texPath>
					<graphicClass>Graphic_Single</graphicClass>
					<drawSize>(2.25, 2.25)</drawSize>
					<shaderType>Transparent</shaderType>
				</graphicData>
			</li>
			<li>
				<tick>16</tick>
				<offset>(0,1,-0.025)</offset>
				<graphicData>
					<texPath>Yuran/Things/Building/Furniture/MilkingMachine/Body/Dildo/L2</texPath>
					<graphicClass>Graphic_Single</graphicClass>
					<drawSize>(2.25, 2.25)</drawSize>
					<shaderType>Transparent</shaderType>
				</graphicData>
			</li>
			<li>
				<tick>20</tick>
				<offset>(0,1,-0.025)</offset>
				<graphicData>
					<texPath>Yuran/Things/Building/Furniture/MilkingMachine/Body/Dildo/4</texPath>
					<graphicClass>Graphic_Single</graphicClass>
					<drawSize>(2.25, 2.25)</drawSize>
					<shaderType>Transparent</shaderType>
				</graphicData>
			</li>
			<li>
				<tick>24</tick>
				<offset>(0,1,-0.025)</offset>
				<graphicData>
					<texPath>Yuran/Things/Building/Furniture/MilkingMachine/Body/Dildo/R3</texPath>
					<graphicClass>Graphic_Single</graphicClass>
					<drawSize>(2.25, 2.25)</drawSize>
					<shaderType>Transparent</shaderType>
				</graphicData>
			</li>
			<li>
				<tick>28</tick>
				<offset>(0,1,-0.025)</offset>
				<graphicData>
					<texPath>Yuran/Things/Building/Furniture/MilkingMachine/Body/Dildo/4</texPath>
					<graphicClass>Graphic_Single</graphicClass>
					<drawSize>(2.25, 2.25)</drawSize>
					<shaderType>Transparent</shaderType>
				</graphicData>
			</li>
			<li>
				<tick>32</tick>
				<offset>(0,1,-0.025)</offset>
				<graphicData>
					<texPath>Yuran/Things/Building/Furniture/MilkingMachine/Body/Dildo/L2</texPath>
					<graphicClass>Graphic_Single</graphicClass>
					<drawSize>(2.25, 2.25)</drawSize>
					<shaderType>Transparent</shaderType>
				</graphicData>
			</li>
			<li>
				<tick>36</tick>
				<offset>(0,1,-0.025)</offset>
				<graphicData>
					<texPath>Yuran/Things/Building/Furniture/MilkingMachine/Body/Dildo/4</texPath>
					<graphicClass>Graphic_Single</graphicClass>
					<drawSize>(2.25, 2.25)</drawSize>
					<shaderType>Transparent</shaderType>
				</graphicData>
			</li>
			<li>
				<tick>40</tick>
				<offset>(0,1,-0.025)</offset>
				<graphicData>
					<texPath>Yuran/Things/Building/Furniture/MilkingMachine/Body/Dildo/R3</texPath>
					<graphicClass>Graphic_Single</graphicClass>
					<drawSize>(2.25, 2.25)</drawSize>
					<shaderType>Transparent</shaderType>
				</graphicData>
			</li>
			<li>
				<tick>44</tick>
				<offset>(0,1,-0.025)</offset>
				<graphicData>
					<texPath>Yuran/Things/Building/Furniture/MilkingMachine/Body/Dildo/4</texPath>
					<graphicClass>Graphic_Single</graphicClass>
					<drawSize>(2.25, 2.25)</drawSize>
					<shaderType>Transparent</shaderType>
				</graphicData>
			</li>
			<li>
				<tick>55</tick>
				<offset>(0,1,-0.025)</offset>
				<graphicData>
					<texPath>Yuran/Things/Building/Furniture/MilkingMachine/Body/Dildo/5</texPath>
					<graphicClass>Graphic_Single</graphicClass>
					<drawSize>(2.25, 2.25)</drawSize>
					<shaderType>Transparent</shaderType>
				</graphicData>
			</li>
		</bedAnimationSettings>
	</YR_Hentai_Prime_AnimationBed.BedAnimationDef>
</Defs>
