<?xml version="1.0" encoding="utf-8"?>
<LanguageData>

  <YR_TentacleWiggle_Hediff.stages.0.label>触手摆动</YR_TentacleWiggle_Hediff.stages.0.label>
  <YR_TentacleWiggle_Hediff.stages.0.description>再来！多鞭打我的身体!</YR_TentacleWiggle_Hediff.stages.0.description>

  <YR_Tentacle_Hediff.stages.0.label>沉浸在快乐中</YR_Tentacle_Hediff.stages.0.label>
  <YR_Tentacle_Hediff.stages.0.description>呀~! 要去了!</YR_Tentacle_Hediff.stages.0.description>
  
  <YR_Pregnant_Thought.stages.1.label>我能感觉到我的孩子</YR_Pregnant_Thought.stages.1.label>
  <YR_Pregnant_Thought.stages.1.description>哦，我的孩子在我的肚子里吃得很饱!</YR_Pregnant_Thought.stages.1.description>
  <YR_Pregnant_Thought.stages.2.label>我很快就能见到我的孩子了</YR_Pregnant_Thought.stages.2.label>
  <YR_Pregnant_Thought.stages.2.description>呵呵!我很期待!</YR_Pregnant_Thought.stages.2.description>

  <YR_EggVibrator_Hediff.stages.0.label>跳蛋振动器激活</YR_EggVibrator_Hediff.stages.0.label>
  <YR_EggVibrator_Hediff.stages.0.description>呀~...它在振动...在我的身体里...。</YR_EggVibrator_Hediff.stages.0.description>
  
  
</LanguageData>